gs_conv_help/__init__.py
gs_conv_help/db_handler.py
gs_conv_help/gs_global.py
gs_conv_help/i18n.py
gs_conv_help/menu_handler.py
gs_conv_help/post_handler.py
gs_conv_help/pre_handler.py
gs_conv_help/response_cards.py
gs_conv_help-1.0.2.dist-info/LICENSE
gs_conv_help-1.0.2.dist-info/METADATA
gs_conv_help-1.0.2.dist-info/WHEEL
gs_conv_help-1.0.2.dist-info/top_level.txt
gs_conv_help-1.0.2.dist-info/RECORD
