Metadata-Version: 2.1
Name: gs-conv-help
Version: 1.0.2
Summary: This repository contains artifacts to help accelerate development of conversational interfaces using Rasa & Gip
Home-page: UNKNOWN
Author: gupshup_gip
Author-email: rahul.meka@gupshup.io
License: UNKNOWN
Platform: UNKNOWN
Classifier: Programming Language :: Python :: 3
Classifier: License :: OSI Approved :: MIT License
Classifier: Operating System :: OS Independent
Requires-Python: <3.9
License-File: LICENSE
Requires-Dist: pymongo (>=3.0)
Requires-Dist: pandas (>=1.0)
Requires-Dist: pyyaml (>=5.0)
Requires-Dist: fuzzywuzzy (>=0.18.0)
